Workbook

Sheet Dashboard
A1: SGX Equity Sales — Corporate Actions Dashboard
A2: =" Lookback window: " & Settings!$B$4 & " weeks | Since " & TEXT(Settings!$B$5,"DD-MMM-YYYY") -> Lookback window: 4 weeks | Since 10-Aug-2026
A4: Change the lookback window and thresholds on the Settings tab — everything below updates from there.
A6: Ticker | B6: Name | C6: Buyback Flag | D6: Volume Flag | E6: Dividend Flag | F6: Split/Rights Flag | G6: M&A/Board Flag | H6: Total Flags | I6: Status
A7: =Universe!A12 -> D05 SP Equity | B7: =Universe!B12 | C7: =Buyback_Tracker!F5 | D7: =Buyback_Tracker!J5 | E7: =Dividend_Tracker!H5 | F7: =Splits_Rights_Tracker!G5 | G7: =_xlfn.TEXTJOIN(", ",TRUE(),IF(MA_Board_Tracker!$A$7:$A$16=A7,MA_Board_Tracker!$H$7:$H$16,"")) | H7: =SUMPRODUCT(--(C7<>""))+SUMPRODUCT(--(D7<>""))+SUMPRODUCT(--(E7<>""))+SUMPRODUCT(--(F7<>""))+SUMPRODUCT(--(G7<>"")) -> 0 | I7: =IF(H7>=2,"🔴 REVIEW NOW",IF(H7=1,"🟡 WATCH","🟢 QUIET")) -> 🟢 QUIET
A8: =Universe!A13 -> O39 SP Equity | B8: =Universe!B13 | C8: =Buyback_Tracker!F6 | D8: =Buyback_Tracker!J6 | E8: =Dividend_Tracker!H6 | F8: =Splits_Rights_Tracker!G6 | G8: =_xlfn.TEXTJOIN(", ",TRUE(),IF(MA_Board_Tracker!$A$7:$A$16=A8,MA_Board_Tracker!$H$7:$H$16,"")) | H8: =SUMPRODUCT(--(C8<>""))+SUMPRODUCT(--(D8<>""))+SUMPRODUCT(--(E8<>""))+SUMPRODUCT(--(F8<>""))+SUMPRODUCT(--(G8<>"")) -> 0 | I8: =IF(H8>=2,"🔴 REVIEW NOW",IF(H8=1,"🟡 WATCH","🟢 QUIET")) -> 🟢 QUIET
A9: =Universe!A14 -> U11 SP Equity | B9: =Universe!B14 | C9: =Buyback_Tracker!F7 | D9: =Buyback_Tracker!J7 | E9: =Dividend_Tracker!H7 | F9: =Splits_Rights_Tracker!G7 | G9: =_xlfn.TEXTJOIN(", ",TRUE(),IF(MA_Board_Tracker!$A$7:$A$16=A9,MA_Board_Tracker!$H$7:$H$16,"")) | H9: =SUMPRODUCT(--(C9<>""))+SUMPRODUCT(--(D9<>""))+SUMPRODUCT(--(E9<>""))+SUMPRODUCT(--(F9<>""))+SUMPRODUCT(--(G9<>"")) -> 0 | I9: =IF(H9>=2,"🔴 REVIEW NOW",IF(H9=1,"🟡 WATCH","🟢 QUIET")) -> 🟢 QUIET
A10: =Universe!A15 -> Z74 SP Equity | B10: =Universe!B15 | C10: =Buyback_Tracker!F8 | D10: =Buyback_Tracker!J8 | E10: =Dividend_Tracker!H8 | F10: =Splits_Rights_Tracker!G8 | G10: =_xlfn.TEXTJOIN(", ",TRUE(),IF(MA_Board_Tracker!$A$7:$A$16=A10,MA_Board_Tracker!$H$7:$H$16,"")) | H10: =SUMPRODUCT(--(C10<>""))+SUMPRODUCT(--(D10<>""))+SUMPRODUCT(--(E10<>""))+SUMPRODUCT(--(F10<>""))+SUMPRODUCT(--(G10<>"")) -> 0 | I10: =IF(H10>=2,"🔴 REVIEW NOW",IF(H10=1,"🟡 WATCH","🟢 QUIET")) -> 🟢 QUIET
A11: =Universe!A16 -> BN4 SP Equity | B11: =Universe!B16 | C11: =Buyback_Tracker!F9 | D11: =Buyback_Tracker!J9 | E11: =Dividend_Tracker!H9 | F11: =Splits_Rights_Tracker!G9 | G11: =_xlfn.TEXTJOIN(", ",TRUE(),IF(MA_Board_Tracker!$A$7:$A$16=A11,MA_Board_Tracker!$H$7:$H$16,"")) | H11: =SUMPRODUCT(--(C11<>""))+SUMPRODUCT(--(D11<>""))+SUMPRODUCT(--(E11<>""))+SUMPRODUCT(--(F11<>""))+SUMPRODUCT(--(G11<>"")) -> 0 | I11: =IF(H11>=2,"🔴 REVIEW NOW",IF(H11=1,"🟡 WATCH","🟢 QUIET")) -> 🟢 QUIET
A12: =Universe!A17 -> C38U SP Equity | B12: =Universe!B17 | C12: =Buyback_Tracker!F10 | D12: =Buyback_Tracker!J10 | E12: =Dividend_Tracker!H10 | F12: =Splits_Rights_Tracker!G10 | G12: =_xlfn.TEXTJOIN(", ",TRUE(),IF(MA_Board_Tracker!$A$7:$A$16=A12,MA_Board_Tracker!$H$7:$H$16,"")) | H12: =SUMPRODUCT(--(C12<>""))+SUMPRODUCT(--(D12<>""))+SUMPRODUCT(--(E12<>""))+SUMPRODUCT(--(F12<>""))+SUMPRODUCT(--(G12<>"")) -> 0 | I12: =IF(H12>=2,"🔴 REVIEW NOW",IF(H12=1,"🟡 WATCH","🟢 QUIET")) -> 🟢 QUIET

Sheet Settings
A1: SGX Corporate Actions Tracker — Settings
A2: Adjustable inputs (blue/yellow) drive every flag on every tab. Change here, not on the tracker tabs.
A3: Setting | B3: Value | C3: Notes
A4: Lookback window (weeks) | B4: 4 | C4: Number of weeks counted as 'recent'. All tracker tabs reference this.
A5: Lookback start date | B5: =TODAY()-(B4*7) -> 46244 | C5: Calculated — do not edit.
A6: Buyback flag threshold (% shares out decline) | B6: -0.005 | C6: Flags a ticker if shares outstanding fell by at least this % over the lookback window. Stored as a fraction, e.g. -0.005 = -0.5%. Chosen as a starting point — tighten/loosen based on what noise level you see.
A7: Volume spike multiple (x 30D avg) | B7: 2 | C7: Flags a ticker if today's volume is at least this multiple of its 30-day average volume — a secondary, market-based corroboration of buyback activity.
A8: Dividend flag rule | B8: New declaration OR special-type dividend within lookback window | C8: Any declaration in the window is flagged since dividend events are comparatively rare and binary.
A9: Split/Rights flag rule | B9: Any occurrence within lookback window | C9: Binary flag — these are rare corporate events.
A11: Legend
A12: Yellow fill / blue text | B12: Input cell — safe to edit
A13: Black text | B13: Formula — do not overwrite
A14: Green text | B14: Link pulling from another tab
A15: Orange fill | B15: Bloomberg field to VERIFY in FLDS<GO> before relying on it — Bloomberg periodically renames/retires fields, and I could not test these live
A16: Red fill on a Flag cell | B16: Significant activity detected in the lookback window
A19: How this workbook refreshes
A20: All BDP/BDH/BDS formulas are live Bloomberg Excel Add-in functions. With a Bloomberg Terminal running and logged in, this file recalculates in real time. Force a full refresh anytime with Ctrl+Alt+F9. Opened without a live Terminal session, these cells will show blank or an error value instead of data.

Sheet Universe
A1: Universe — SGX-Listed Stocks
A2: Bloomberg's BDP/BDS/BDH functions query one ticker at a time — there is no single formula that dynamically screens 'every SGX-listed name.' Two ways to populate column A below:
A4: 1) Best coverage: in Bloomberg Terminal run EQS<GO> → new screen → Exchange = Singapore Exchange, Primary Listing = Yes → export tickers → paste into column A from row 8 down.
A6: 2) Quick start (built into row 8 below): pulls the ~200 most liquid/relevant names via the FTSE ST All-Share Index membership list, which covers the names an equity sales desk actually trades. Thinly-traded shells outside this index rarely matter for flow coverage, but re-run option 1 periodically if you need true full-exchange coverage.
A9: Ticker (Bloomberg) | B9: Company Name | C9: GICS Sector | D9: Primary Exchange | E9: Include in Trackers? (Y/N)
A10: =IFERROR(bds("FSTAS Index","INDX_MEMBERS"),NA()) -> #N/A
A11: — Example rows below (delete once you paste your real universe) —
A12: D05 SP Equity | B12: =IFERROR(bdp(A12,"NAME"),"") | C12: =IFERROR(bdp(A12,"GICS_SECTOR_NAME"),"") | D12: =IFERROR(bdp(A12,"PRIMARY_EXCHANGE_NAME"),"") | E12: Y
A13: O39 SP Equity | B13: =IFERROR(bdp(A13,"NAME"),"") | C13: =IFERROR(bdp(A13,"GICS_SECTOR_NAME"),"") | D13: =IFERROR(bdp(A13,"PRIMARY_EXCHANGE_NAME"),"") | E13: Y
A14: U11 SP Equity | B14: =IFERROR(bdp(A14,"NAME"),"") | C14: =IFERROR(bdp(A14,"GICS_SECTOR_NAME"),"") | D14: =IFERROR(bdp(A14,"PRIMARY_EXCHANGE_NAME"),"") | E14: Y
A15: Z74 SP Equity | B15: =IFERROR(bdp(A15,"NAME"),"") | C15: =IFERROR(bdp(A15,"GICS_SECTOR_NAME"),"") | D15: =IFERROR(bdp(A15,"PRIMARY_EXCHANGE_NAME"),"") | E15: Y
A16: BN4 SP Equity | B16: =IFERROR(bdp(A16,"NAME"),"") | C16: =IFERROR(bdp(A16,"GICS_SECTOR_NAME"),"") | D16: =IFERROR(bdp(A16,"PRIMARY_EXCHANGE_NAME"),"") | E16: Y
A17: C38U SP Equity | B17: =IFERROR(bdp(A17,"NAME"),"") | C17: =IFERROR(bdp(A17,"GICS_SECTOR_NAME"),"") | D17: =IFERROR(bdp(A17,"PRIMARY_EXCHANGE_NAME"),"") | E17: Y

Sheet Buyback_Tracker
A1: Share Buyback Tracker
A2: Primary signal: change in shares outstanding over the lookback window (a buyback mechanically reduces EQY_SH_OUT). Secondary corroboration: today's volume vs 30-day average, since buyback execution often shows up as elevated volume.
A4: Ticker | B4: Name | C4: Shares Out — Today | D4: Shares Out — {Lookback} Wks Ago | E4: % Change | F4: Buyback Flag | G4: Avg Vol (30D) | H4: Volume — Today | I4: Vol vs Avg (x) | J4: Volume Flag
A5: =Universe!A12 -> D05 SP Equity | B5: =IFERROR(bdp(A5,"NAME"),"") | C5: =IFERROR(bdp(A5,"EQY_SH_OUT"),NA()) -> #N/A | D5: =IFERROR(bdh(A5,"EQY_SH_OUT",Settings!$B$5,Settings!$B$5),NA()) -> #N/A | E5: =IFERROR((C5-D5)/D5,NA()) -> #N/A | F5: =IF(ISNUMBER(E5),IF(E5<=Settings!$B$6,"⚠ BUYBACK ACTIVITY",""),"") | G5: =IFERROR(bdp(A5,"VOLUME_AVG_30D"),NA()) -> #N/A | H5: =IFERROR(bdp(A5,"PX_VOLUME"),NA()) -> #N/A | I5: =IFERROR(H5/G5,NA()) -> #N/A | J5: =IF(ISNUMBER(I5),IF(I5>=Settings!$B$7,"⚠ VOL SPIKE",""),"")
A6: =Universe!A13 -> O39 SP Equity | B6: =IFERROR(bdp(A6,"NAME"),"") | C6: =IFERROR(bdp(A6,"EQY_SH_OUT"),NA()) -> #N/A | D6: =IFERROR(bdh(A6,"EQY_SH_OUT",Settings!$B$5,Settings!$B$5),NA()) -> #N/A | E6: =IFERROR((C6-D6)/D6,NA()) -> #N/A | F6: =IF(ISNUMBER(E6),IF(E6<=Settings!$B$6,"⚠ BUYBACK ACTIVITY",""),"") | G6: =IFERROR(bdp(A6,"VOLUME_AVG_30D"),NA()) -> #N/A | H6: =IFERROR(bdp(A6,"PX_VOLUME"),NA()) -> #N/A | I6: =IFERROR(H6/G6,NA()) -> #N/A | J6: =IF(ISNUMBER(I6),IF(I6>=Settings!$B$7,"⚠ VOL SPIKE",""),"")
A7: =Universe!A14 -> U11 SP Equity | B7: =IFERROR(bdp(A7,"NAME"),"") | C7: =IFERROR(bdp(A7,"EQY_SH_OUT"),NA()) -> #N/A | D7: =IFERROR(bdh(A7,"EQY_SH_OUT",Settings!$B$5,Settings!$B$5),NA()) -> #N/A | E7: =IFERROR((C7-D7)/D7,NA()) -> #N/A | F7: =IF(ISNUMBER(E7),IF(E7<=Settings!$B$6,"⚠ BUYBACK ACTIVITY",""),"") | G7: =IFERROR(bdp(A7,"VOLUME_AVG_30D"),NA()) -> #N/A | H7: =IFERROR(bdp(A7,"PX_VOLUME"),NA()) -> #N/A | I7: =IFERROR(H7/G7,NA()) -> #N/A | J7: =IF(ISNUMBER(I7),IF(I7>=Settings!$B$7,"⚠ VOL SPIKE",""),"")
A8: =Universe!A15 -> Z74 SP Equity | B8: =IFERROR(bdp(A8,"NAME"),"") | C8: =IFERROR(bdp(A8,"EQY_SH_OUT"),NA()) -> #N/A | D8: =IFERROR(bdh(A8,"EQY_SH_OUT",Settings!$B$5,Settings!$B$5),NA()) -> #N/A | E8: =IFERROR((C8-D8)/D8,NA()) -> #N/A | F8: =IF(ISNUMBER(E8),IF(E8<=Settings!$B$6,"⚠ BUYBACK ACTIVITY",""),"") | G8: =IFERROR(bdp(A8,"VOLUME_AVG_30D"),NA()) -> #N/A | H8: =IFERROR(bdp(A8,"PX_VOLUME"),NA()) -> #N/A | I8: =IFERROR(H8/G8,NA()) -> #N/A | J8: =IF(ISNUMBER(I8),IF(I8>=Settings!$B$7,"⚠ VOL SPIKE",""),"")
A9: =Universe!A16 -> BN4 SP Equity | B9: =IFERROR(bdp(A9,"NAME"),"") | C9: =IFERROR(bdp(A9,"EQY_SH_OUT"),NA()) -> #N/A | D9: =IFERROR(bdh(A9,"EQY_SH_OUT",Settings!$B$5,Settings!$B$5),NA()) -> #N/A | E9: =IFERROR((C9-D9)/D9,NA()) -> #N/A | F9: =IF(ISNUMBER(E9),IF(E9<=Settings!$B$6,"⚠ BUYBACK ACTIVITY",""),"") | G9: =IFERROR(bdp(A9,"VOLUME_AVG_30D"),NA()) -> #N/A | H9: =IFERROR(bdp(A9,"PX_VOLUME"),NA()) -> #N/A | I9: =IFERROR(H9/G9,NA()) -> #N/A | J9: =IF(ISNUMBER(I9),IF(I9>=Settings!$B$7,"⚠ VOL SPIKE",""),"")
A10: =Universe!A17 -> C38U SP Equity | B10: =IFERROR(bdp(A10,"NAME"),"") | C10: =IFERROR(bdp(A10,"EQY_SH_OUT"),NA()) -> #N/A | D10: =IFERROR(bdh(A10,"EQY_SH_OUT",Settings!$B$5,Settings!$B$5),NA()) -> #N/A | E10: =IFERROR((C10-D10)/D10,NA()) -> #N/A | F10: =IF(ISNUMBER(E10),IF(E10<=Settings!$B$6,"⚠ BUYBACK ACTIVITY",""),"") | G10: =IFERROR(bdp(A10,"VOLUME_AVG_30D"),NA()) -> #N/A | H10: =IFERROR(bdp(A10,"PX_VOLUME"),NA()) -> #N/A | I10: =IFERROR(H10/G10,NA()) -> #N/A | J10: =IF(ISNUMBER(I10),IF(I10>=Settings!$B$7,"⚠ VOL SPIKE",""),"")

Sheet Dividend_Tracker
A1: Dividend & Distribution Tracker
A2: Flags any dividend/distribution declared within the lookback window, and separately flags special dividends (which sales desks usually want surfaced regardless of window).
A4: Ticker | B4: Name | C4: Declared Date | D4: Ex-Date | E4: Div/Unit (Local Ccy) | F4: Dividend Type | G4: In Lookback Window? | H4: Flag
A5: =Universe!A12 -> D05 SP Equity | B5: =IFERROR(bdp(A5,"NAME"),"") | C5: =IFERROR(bdp(A5,"DVD_DECLARED_DT"),NA()) -> #N/A | D5: =IFERROR(bdp(A5,"DVD_EX_DT"),NA()) -> #N/A | E5: =IFERROR(bdp(A5,"DVD_SH_LAST"),NA()) -> #N/A | F5: =IFERROR(bdp(A5,"DVD_TYPE"),"") | G5: =IF(ISNUMBER(C5),IF(C5>=Settings!$B$5,"Y","N"),"") | H5: =IF(G5="Y",IF(ISNUMBER(SEARCH("Special",F5)),"⚠ SPECIAL DIVIDEND","⚠ NEW DIVIDEND"),IF(ISNUMBER(SEARCH("Special",F5)),"⚠ SPECIAL DIVIDEND",""))
A6: =Universe!A13 -> O39 SP Equity | B6: =IFERROR(bdp(A6,"NAME"),"") | C6: =IFERROR(bdp(A6,"DVD_DECLARED_DT"),NA()) -> #N/A | D6: =IFERROR(bdp(A6,"DVD_EX_DT"),NA()) -> #N/A | E6: =IFERROR(bdp(A6,"DVD_SH_LAST"),NA()) -> #N/A | F6: =IFERROR(bdp(A6,"DVD_TYPE"),"") | G6: =IF(ISNUMBER(C6),IF(C6>=Settings!$B$5,"Y","N"),"") | H6: =IF(G6="Y",IF(ISNUMBER(SEARCH("Special",F6)),"⚠ SPECIAL DIVIDEND","⚠ NEW DIVIDEND"),IF(ISNUMBER(SEARCH("Special",F6)),"⚠ SPECIAL DIVIDEND",""))
A7: =Universe!A14 -> U11 SP Equity | B7: =IFERROR(bdp(A7,"NAME"),"") | C7: =IFERROR(bdp(A7,"DVD_DECLARED_DT"),NA()) -> #N/A | D7: =IFERROR(bdp(A7,"DVD_EX_DT"),NA()) -> #N/A | E7: =IFERROR(bdp(A7,"DVD_SH_LAST"),NA()) -> #N/A | F7: =IFERROR(bdp(A7,"DVD_TYPE"),"") | G7: =IF(ISNUMBER(C7),IF(C7>=Settings!$B$5,"Y","N"),"") | H7: =IF(G7="Y",IF(ISNUMBER(SEARCH("Special",F7)),"⚠ SPECIAL DIVIDEND","⚠ NEW DIVIDEND"),IF(ISNUMBER(SEARCH("Special",F7)),"⚠ SPECIAL DIVIDEND",""))
A8: =Universe!A15 -> Z74 SP Equity | B8: =IFERROR(bdp(A8,"NAME"),"") | C8: =IFERROR(bdp(A8,"DVD_DECLARED_DT"),NA()) -> #N/A | D8: =IFERROR(bdp(A8,"DVD_EX_DT"),NA()) -> #N/A | E8: =IFERROR(bdp(A8,"DVD_SH_LAST"),NA()) -> #N/A | F8: =IFERROR(bdp(A8,"DVD_TYPE"),"") | G8: =IF(ISNUMBER(C8),IF(C8>=Settings!$B$5,"Y","N"),"") | H8: =IF(G8="Y",IF(ISNUMBER(SEARCH("Special",F8)),"⚠ SPECIAL DIVIDEND","⚠ NEW DIVIDEND"),IF(ISNUMBER(SEARCH("Special",F8)),"⚠ SPECIAL DIVIDEND",""))
A9: =Universe!A16 -> BN4 SP Equity | B9: =IFERROR(bdp(A9,"NAME"),"") | C9: =IFERROR(bdp(A9,"DVD_DECLARED_DT"),NA()) -> #N/A | D9: =IFERROR(bdp(A9,"DVD_EX_DT"),NA()) -> #N/A | E9: =IFERROR(bdp(A9,"DVD_SH_LAST"),NA()) -> #N/A | F9: =IFERROR(bdp(A9,"DVD_TYPE"),"") | G9: =IF(ISNUMBER(C9),IF(C9>=Settings!$B$5,"Y","N"),"") | H9: =IF(G9="Y",IF(ISNUMBER(SEARCH("Special",F9)),"⚠ SPECIAL DIVIDEND","⚠ NEW DIVIDEND"),IF(ISNUMBER(SEARCH("Special",F9)),"⚠ SPECIAL DIVIDEND",""))
A10: =Universe!A17 -> C38U SP Equity | B10: =IFERROR(bdp(A10,"NAME"),"") | C10: =IFERROR(bdp(A10,"DVD_DECLARED_DT"),NA()) -> #N/A | D10: =IFERROR(bdp(A10,"DVD_EX_DT"),NA()) -> #N/A | E10: =IFERROR(bdp(A10,"DVD_SH_LAST"),NA()) -> #N/A | F10: =IFERROR(bdp(A10,"DVD_TYPE"),"") | G10: =IF(ISNUMBER(C10),IF(C10>=Settings!$B$5,"Y","N"),"") | H10: =IF(G10="Y",IF(ISNUMBER(SEARCH("Special",F10)),"⚠ SPECIAL DIVIDEND","⚠ NEW DIVIDEND"),IF(ISNUMBER(SEARCH("Special",F10)),"⚠ SPECIAL DIVIDEND",""))

Sheet Splits_Rights_Tracker
A1: Splits, Bonus Issues & Rights Issues Tracker
A2: These are rare, discrete events — any occurrence inside the lookback window is flagged. Fields here are lower-confidence mnemonics; verify all of them in FLDS<GO> before trusting this tab.
A4: Ticker | B4: Name | C4: Latest Corp. Action Date | D4: Action Type | E4: Ratio / Terms | F4: In Lookback Window? | G4: Flag
A5: =Universe!A12 -> D05 SP Equity | B5: =IFERROR(bdp(A5,"NAME"),"") | C5: =IFERROR(bdp(A5,"EQY_SPLIT_DT"),NA()) -> #N/A | F5: =IF(ISNUMBER(C5),IF(C5>=Settings!$B$5,"Y","N"),"") | G5: =IF(F5="Y","⚠ SPLIT/RIGHTS EVENT","")
A6: =Universe!A13 -> O39 SP Equity | B6: =IFERROR(bdp(A6,"NAME"),"") | C6: =IFERROR(bdp(A6,"EQY_SPLIT_DT"),NA()) -> #N/A | F6: =IF(ISNUMBER(C6),IF(C6>=Settings!$B$5,"Y","N"),"") | G6: =IF(F6="Y","⚠ SPLIT/RIGHTS EVENT","")
A7: =Universe!A14 -> U11 SP Equity | B7: =IFERROR(bdp(A7,"NAME"),"") | C7: =IFERROR(bdp(A7,"EQY_SPLIT_DT"),NA()) -> #N/A | F7: =IF(ISNUMBER(C7),IF(C7>=Settings!$B$5,"Y","N"),"") | G7: =IF(F7="Y","⚠ SPLIT/RIGHTS EVENT","")
A8: =Universe!A15 -> Z74 SP Equity | B8: =IFERROR(bdp(A8,"NAME"),"") | C8: =IFERROR(bdp(A8,"EQY_SPLIT_DT"),NA()) -> #N/A | F8: =IF(ISNUMBER(C8),IF(C8>=Settings!$B$5,"Y","N"),"") | G8: =IF(F8="Y","⚠ SPLIT/RIGHTS EVENT","")
A9: =Universe!A16 -> BN4 SP Equity | B9: =IFERROR(bdp(A9,"NAME"),"") | C9: =IFERROR(bdp(A9,"EQY_SPLIT_DT"),NA()) -> #N/A | F9: =IF(ISNUMBER(C9),IF(C9>=Settings!$B$5,"Y","N"),"") | G9: =IF(F9="Y","⚠ SPLIT/RIGHTS EVENT","")
A10: =Universe!A17 -> C38U SP Equity | B10: =IFERROR(bdp(A10,"NAME"),"") | C10: =IFERROR(bdp(A10,"EQY_SPLIT_DT"),NA()) -> #N/A | F10: =IF(ISNUMBER(C10),IF(C10>=Settings!$B$5,"Y","N"),"") | G10: =IF(F10="Y","⚠ SPLIT/RIGHTS EVENT","")

Sheet MA_Board_Tracker
A1: M&A, Delisting & Board Changes — Manual Log
A2: No single Bloomberg formula reliably screens for M&A announcements, delistings or board changes across a universe the way BDP/BDH do for prices or dividends — these are best monitored via Bloomberg's MA<GO> (M&A) and NI SGMA <GO> (Singapore M&A news) screens, or a company news monitor. Log entries here as they're spotted; the Date column drives the flag and the Dashboard rollup so the rest of the workbook still treats this tab consistently.
A6: Ticker | B6: Name | C6: Event Type | D6: Date | E6: Source / Link | F6: Notes | G6: In Lookback Window? | H6: Flag
G7: =IF(ISNUMBER(D7),IF(D7>=Settings!$B$5,"Y","N"),"") | H7: =IF(G7="Y","⚠ "&IF(C7="","EVENT",UPPER(C7)),"")
G8: =IF(ISNUMBER(D8),IF(D8>=Settings!$B$5,"Y","N"),"") | H8: =IF(G8="Y","⚠ "&IF(C8="","EVENT",UPPER(C8)),"")
G9: =IF(ISNUMBER(D9),IF(D9>=Settings!$B$5,"Y","N"),"") | H9: =IF(G9="Y","⚠ "&IF(C9="","EVENT",UPPER(C9)),"")
G10: =IF(ISNUMBER(D10),IF(D10>=Settings!$B$5,"Y","N"),"") | H10: =IF(G10="Y","⚠ "&IF(C10="","EVENT",UPPER(C10)),"")
G11: =IF(ISNUMBER(D11),IF(D11>=Settings!$B$5,"Y","N"),"") | H11: =IF(G11="Y","⚠ "&IF(C11="","EVENT",UPPER(C11)),"")
G12: =IF(ISNUMBER(D12),IF(D12>=Settings!$B$5,"Y","N"),"") | H12: =IF(G12="Y","⚠ "&IF(C12="","EVENT",UPPER(C12)),"")
G13: =IF(ISNUMBER(D13),IF(D13>=Settings!$B$5,"Y","N"),"") | H13: =IF(G13="Y","⚠ "&IF(C13="","EVENT",UPPER(C13)),"")
G14: =IF(ISNUMBER(D14),IF(D14>=Settings!$B$5,"Y","N"),"") | H14: =IF(G14="Y","⚠ "&IF(C14="","EVENT",UPPER(C14)),"")
G15: =IF(ISNUMBER(D15),IF(D15>=Settings!$B$5,"Y","N"),"") | H15: =IF(G15="Y","⚠ "&IF(C15="","EVENT",UPPER(C15)),"")
G16: =IF(ISNUMBER(D16),IF(D16>=Settings!$B$5,"Y","N"),"") | H16: =IF(G16="Y","⚠ "&IF(C16="","EVENT",UPPER(C16)),"")
